{
    "CIL_CCDB": {
        "Status": {
            "Deleted": false,
            "Is_public": true
        },
        "CIL": {
            "CORE": {
                "TERMSANDCONDITIONS": {
                    "free_text": "attribution_cc_by"
                },
                "IMAGEDESCRIPTION": {
                    "free_text": "Light micrograph, alcian blue PAS staining of gastric mucosa from N 18 month old gastrick H,K,ATPase null mouse, 100 x"
                },
                "CELLTYPE": [
                    {
                        "onto_name": "parietal cell",
                        "onto_id": "CL:0000162"
                    },
                    {
                        "free_text": "zymogen"
                    },
                    {
                        "free_text": "mucus"
                    }
                ],
                "CELLULARCOMPONENT": [
                    {
                        "free_text": "mitochondria"
                    },
                    {
                        "free_text": "nuclei"
                    },
                    {
                        "free_text": "secretion granules"
                    }
                ],
                "NCBIORGANISMALCLASSIFICATION": [
                    {
                        "onto_name": "Mus musculus",
                        "onto_id": "NCBITaxon:10090"
                    }
                ],
                "IMAGINGMODE": [
                    {
                        "onto_name": "modes of light microscopy",
                        "onto_id": "FBbi:00000345"
                    }
                ],
                "ITEMTYPE": [
                    {
                        "free_text": "micrograph"
                    }
                ],
                "PREPARATION": [
                    {
                        "free_text": "Paraformaldehyde"
                    }
                ],
                "ATTRIBUTION": {
                    "Contributors": [
                        "Marian Miller"
                    ]
                },
                "DIMENSION": [
                    {
                        "Space": {
                            "axis": "X",
                            "Pixel_size": {
                                "value": "4800",
                                "unit": "microns"
                            },
                            "Image_size": "600"
                        }
                    },
                    {
                        "Space": {
                            "axis": "Y",
                            "Pixel_size": {
                                "value": "3771",
                                "unit": "microns"
                            },
                            "Image_size": "600"
                        }
                    },
                    {
                        "Space": {
                            "axis": "Z",
                            "Pixel_size": {
                                "value": "3771",
                                "unit": "microns"
                            },
                            "Image_size": "600"
                        }
                    }
                ]
            },
            "Image_files": [
                {
                    "Mime_type": "image/tif",
                    "File_path": "48201.tif",
                    "Size": 54400000,
                    "File_type": "OME_tif"
                },
                {
                    "Mime_type": "image/jpeg; charset=utf-8",
                    "File_path": "48201.jpg",
                    "Size": 3220578,
                    "File_type": "Jpeg"
                },
                {
                    "Mime_type": "application/zip",
                    "File_path": "48201.zip",
                    "Size": 54307942,
                    "File_type": "Zip"
                },
                {
                    "Mime_type": "image/tiff",
                    "File_path": "48201_orig.tif",
                    "Size": 54307804,
                    "File_type": "OME_tif"
                }
            ]
        },
        "Data_type": {
            "Time_series": false,
            "Z_stack": false,
            "Video": false,
            "Still_image": true
        },
        "Citation": {
            "DOI": "doi:10.7295/W9CIL48201",
            "ARK": "ark:/b7295/w9cil48201",
            "Title": "Marian Miller (2016) CIL:48201, Mus musculus, parietal cell, zymogen, mucus. CIL. Dataset"
        }
    }
}